superrocket/__init__.py
superrocket/api.py
superrocket/superrocket.py
superrocket-0.3.0.dist-info/DESCRIPTION.rst
superrocket-0.3.0.dist-info/METADATA
superrocket-0.3.0.dist-info/RECORD
superrocket-0.3.0.dist-info/WHEEL
superrocket-0.3.0.dist-info/entry_points.txt
superrocket-0.3.0.dist-info/metadata.json
superrocket-0.3.0.dist-info/top_level.txt
