Metadata-Version: 2.0
Name: superrocket
Version: 0.3.0
Summary: A supervisord process notification for rocketchat.
Home-page: https://github.com/ansrivas/superrocket
Author: Ankur Srivastava
Author-email: ankur.srivastava@email.de
License: UNKNOWN
Download-URL: https://github.com/ansrivas/superrocket/archive/0.3.0.tar.gz
Platform: UNKNOWN
Classifier: Programming Language :: Python :: 2
Classifier: Programming Language :: Python :: 2.7
Requires-Dist: supervisor
Requires-Dist: superlance
Requires-Dist: requests
